apyosoenergyapi/__init__.py
apyosoenergyapi/binary_sensor.py
apyosoenergyapi/device_attributes.py
apyosoenergyapi/osoenergy.py
apyosoenergyapi/sensor.py
apyosoenergyapi/session.py
apyosoenergyapi/switch.py
apyosoenergyapi/waterheater.py
apyosoenergyapi/api/__init__.py
apyosoenergyapi/api/osoenergy_async_api.py
apyosoenergyapi/helper/__init__.py
apyosoenergyapi/helper/const.py
apyosoenergyapi/helper/logger.py
apyosoenergyapi/helper/map.py
apyosoenergyapi/helper/osoenergy_exceptions.py
apyosoenergyapi/helper/osoenergy_helper.py
pyosoenergyapi/__init__.py
pyosoenergyapi/binary_sensor.py
pyosoenergyapi/device_attributes.py
pyosoenergyapi/osoenergy.py
pyosoenergyapi/sensor.py
pyosoenergyapi/session.py
pyosoenergyapi/switch.py
pyosoenergyapi/waterheater.py
pyosoenergyapi/api/__init__.py
pyosoenergyapi/api/osoenergy_async_api.py
pyosoenergyapi/helper/__init__.py
pyosoenergyapi/helper/const.py
pyosoenergyapi/helper/logger.py
pyosoenergyapi/helper/map.py
pyosoenergyapi/helper/osoenergy_exceptions.py
pyosoenergyapi/helper/osoenergy_helper.py
pyosoenergyapi-1.2.3.dist-info/licenses/LICENSE
pyosoenergyapi-1.2.3.dist-info/METADATA
pyosoenergyapi-1.2.3.dist-info/WHEEL
pyosoenergyapi-1.2.3.dist-info/top_level.txt
pyosoenergyapi-1.2.3.dist-info/RECORD
